[
  {
    "ID": "31301",
    "Type": 3,
    "Quality": 4,
    "Name": "QCQ171",
    "AmmoType": 13,
    "PriceFluctuation": 0.0592769247415654,
    "Damage": 31,
    "Precision": 16,
    "Recoil": 3,
    "Clip": 30,
    "FiringRate": 0.6,
    "ReloadDuration": 1,
    "Required": "123021,123025,122016",
    "quantity": "1,2,4",
    "Duration": 600,
    "output": 1
  },
  {
    "ID": "31302",
    "Type": 3,
    "Quality": 2,
    "Name": "MP5",
    "AmmoType": 13,
    "PriceFluctuation": 0.0694230386238863,
    "Damage": 28,
    "Precision": 18,
    "Recoil": 4,
    "Clip": 30,
    "FiringRate": 0.8,
    "ReloadDuration": 1,
    "Required": "123021,123025,122016",
    "quantity": "1,1,3",
    "Duration": 120,
    "output": 1
  },
  {
    "ID": "30501",
    "Type": 3,
    "Quality": 3,
    "Name": "P90",
    "AmmoType": 5,
    "PriceFluctuation": 0.0695560045237021,
    "Damage": 31,
    "Precision": 19,
    "Recoil": 5,
    "Clip": 50,
    "FiringRate": 0.9,
    "ReloadDuration": 1,
    "Required": "123021,123025,122016",
    "quantity": "1,2,4",
    "Duration": 360,
    "output": 1
  },
  {
    "ID": "30101",
    "Type": 3,
    "Quality": 4,
    "Name": "维克托",
    "AmmoType": 1,
    "PriceFluctuation": 0.0796518970724936,
    "Damage": 28,
    "Precision": 22,
    "Recoil": 6,
    "Clip": 25,
    "FiringRate": 1.2,
    "ReloadDuration": 1,
    "Required": "123021,123025,122016",
    "quantity": "1,1,4",
    "Duration": 600,
    "output": 1
  },
  {
    "ID": "31303",
    "Type": 3,
    "Quality": 1,
    "Name": "UZI",
    "AmmoType": 13,
    "PriceFluctuation": 0.0896573173052778,
    "Damage": 27,
    "Precision": 18,
    "Recoil": 4,
    "Clip": 30,
    "FiringRate": 0.8,
    "ReloadDuration": 1,
    "Required": "123021,123025,122016",
    "quantity": "1,2,4",
    "Duration": 10,
    "output": 1
  },
  {
    "ID": "31304",
    "Type": 3,
    "Quality": 1,
    "Name": "野牛",
    "AmmoType": 13,
    "PriceFluctuation": 0.0713284047793094,
    "Damage": 30,
    "Precision": 16,
    "Recoil": 3,
    "Clip": 60,
    "FiringRate": 0.6,
    "ReloadDuration": 1,
    "Required": "123021,123025,122016",
    "quantity": "1,1,3",
    "Duration": 10,
    "output": 1
  },
  {
    "ID": "30102",
    "Type": 3,
    "Quality": 2,
    "Name": "SMG45",
    "AmmoType": 1,
    "PriceFluctuation": 0.097648497410614,
    "Damage": 27,
    "Precision": 16,
    "Recoil": 3,
    "Clip": 25,
    "FiringRate": 0.6,
    "ReloadDuration": 1,
    "Required": "123021,123025,122016",
    "quantity": "1,2,4",
    "Duration": 120,
    "output": 1
  },
  {
    "ID": "31401",
    "Type": 3,
    "Quality": 3,
    "Name": "SR-3M",
    "AmmoType": 14,
    "PriceFluctuation": 0.0829539825745099,
    "Damage": 28,
    "Precision": 18,
    "Recoil": 4,
    "Clip": 30,
    "FiringRate": 0.8,
    "ReloadDuration": 1,
    "Required": "123021,123025,122016",
    "quantity": "1,1,4",
    "Duration": 360,
    "output": 1
  },
  {
    "ID": "31305",
    "Type": 3,
    "Quality": 2,
    "Name": "勇士",
    "AmmoType": 13,
    "PriceFluctuation": 0.0890595713593758,
    "Damage": 27,
    "Precision": 16,
    "Recoil": 3,
    "Clip": 30,
    "FiringRate": 0.6,
    "ReloadDuration": 1,
    "Required": "123021,123025,122016",
    "quantity": "1,2,4",
    "Duration": 120,
    "output": 1
  },
  {
    "ID": "30401",
    "Type": 3,
    "Quality": 4,
    "Name": "MP7",
    "AmmoType": 4,
    "PriceFluctuation": 0.056535993968144,
    "Damage": 28,
    "Precision": 18,
    "Recoil": 4,
    "Clip": 30,
    "FiringRate": 0.8,
    "ReloadDuration": 1,
    "Required": "123021,123025,122016",
    "quantity": "1,1,3",
    "Duration": 600,
    "output": 1
  },
  {
    "ID": "31306",
    "Type": 1,
    "Quality": 1,
    "Name": "QSZ92G",
    "AmmoType": 13,
    "PriceFluctuation": 0.0655378971659919,
    "Damage": 35,
    "Precision": 13,
    "Recoil": 2,
    "Clip": 7,
    "FiringRate": 0.3,
    "ReloadDuration": 1,
    "Required": "123021,123025,122016",
    "quantity": "1,2,4",
    "Duration": 10,
    "output": 1
  },
  {
    "ID": "30301",
    "Type": 1,
    "Quality": 2,
    "Name": ".357左轮",
    "AmmoType": 3,
    "PriceFluctuation": 0.0942306862716671,
    "Damage": 59,
    "Precision": 13,
    "Recoil": 2,
    "Clip": 6,
    "FiringRate": 0.3,
    "ReloadDuration": 1,
    "Required": "123021,123025,122016",
    "quantity": "1,1,4",
    "Duration": 120,
    "output": 1
  },
  {
    "ID": "30201",
    "Type": 1,
    "Quality": 3,
    "Name": "沙漠之鹰",
    "AmmoType": 2,
    "PriceFluctuation": 0.0991271404649092,
    "Damage": 50,
    "Precision": 13,
    "Recoil": 2,
    "Clip": 7,
    "FiringRate": 0.3,
    "ReloadDuration": 1,
    "Required": "123021,123025,122016",
    "quantity": "1,2,4",
    "Duration": 360,
    "output": 1
  },
  {
    "ID": "31307",
    "Type": 1,
    "Quality": 2,
    "Name": "G18",
    "AmmoType": 13,
    "PriceFluctuation": 0.0519046503645801,
    "Damage": 24,
    "Precision": 20,
    "Recoil": 5,
    "Clip": 20,
    "FiringRate": 1,
    "ReloadDuration": 1,
    "Required": "123021,123025,122016",
    "quantity": "1,1,3",
    "Duration": 120,
    "output": 1
  },
  {
    "ID": "31308",
    "Type": 1,
    "Quality": 2,
    "Name": "93R",
    "AmmoType": 13,
    "PriceFluctuation": 0.0548585367157253,
    "Damage": 36,
    "Precision": 17,
    "Recoil": 4,
    "Clip": 15,
    "FiringRate": 0.7,
    "ReloadDuration": 1,
    "Required": "123021,123025,122016",
    "quantity": "1,2,4",
    "Duration": 120,
    "output": 1
  },
  {
    "ID": "31309",
    "Type": 1,
    "Quality": 1,
    "Name": "G17",
    "AmmoType": 13,
    "PriceFluctuation": 0.0836084299093397,
    "Damage": 27,
    "Precision": 13,
    "Recoil": 2,
    "Clip": 10,
    "FiringRate": 0.3,
    "ReloadDuration": 1,
    "Required": "123021,123025,122016",
    "quantity": "1,1,4",
    "Duration": 10,
    "output": 1
  },
  {
    "ID": "30103",
    "Type": 1,
    "Quality": 3,
    "Name": "M1911",
    "AmmoType": 1,
    "PriceFluctuation": 0.0593258018083179,
    "Damage": 36,
    "Precision": 15,
    "Recoil": 3,
    "Clip": 10,
    "FiringRate": 0.5,
    "ReloadDuration": 1,
    "Required": "123021,123025,122016",
    "quantity": "1,2,4",
    "Duration": 360,
    "output": 1
  },
  {
    "ID": "30801",
    "Type": 2,
    "Quality": 3,
    "Name": "M4A1",
    "AmmoType": 8,
    "PriceFluctuation": 0.0639257780783838,
    "Damage": 30,
    "Precision": 18,
    "Recoil": 4,
    "Clip": 30,
    "FiringRate": 0.8,
    "ReloadDuration": 1,
    "Required": "123021,123025,122016",
    "quantity": "1,1,3",
    "Duration": 360,
    "output": 1
  },
  {
    "ID": "31001",
    "Type": 2,
    "Quality": 3,
    "Name": "AKM",
    "AmmoType": 10,
    "PriceFluctuation": 0.0984939760108998,
    "Damage": 37,
    "Precision": 16,
    "Recoil": 3,
    "Clip": 30,
    "FiringRate": 0.6,
    "ReloadDuration": 1,
    "Required": "123021,123025,122016",
    "quantity": "1,2,4",
    "Duration": 360,
    "output": 1
  },
  {
    "ID": "30601",
    "Type": 2,
    "Quality": 1,
    "Name": "QBZ95",
    "AmmoType": 6,
    "PriceFluctuation": 0.0812833423781857,
    "Damage": 32,
    "Precision": 17,
    "Recoil": 4,
    "Clip": 30,
    "FiringRate": 0.7,
    "ReloadDuration": 1,
    "Required": "123021,123025,122016",
    "quantity": "1,1,4",
    "Duration": 10,
    "output": 1
  },
  {
    "ID": "30701",
    "Type": 2,
    "Quality": 1,
    "Name": "AKS-74U",
    "AmmoType": 7,
    "PriceFluctuation": 0.0942228656885347,
    "Damage": 30,
    "Precision": 16,
    "Recoil": 3,
    "Clip": 20,
    "FiringRate": 0.6,
    "ReloadDuration": 1,
    "Required": "123021,123025,122016",
    "quantity": "1,2,4",
    "Duration": 10,
    "output": 1
  },
  {
    "ID": "31501",
    "Type": 2,
    "Quality": 4,
    "Name": "ASh-12",
    "AmmoType": 15,
    "PriceFluctuation": 0.0652432868288342,
    "Damage": 44,
    "Precision": 15,
    "Recoil": 3,
    "Clip": 20,
    "FiringRate": 0.5,
    "ReloadDuration": 1,
    "Required": "123021,123025,122016",
    "quantity": "1,1,3",
    "Duration": 600,
    "output": 1
  },
  {
    "ID": "30802",
    "Type": 2,
    "Quality": 4,
    "Name": "K416",
    "AmmoType": 8,
    "PriceFluctuation": 0.0704508969537815,
    "Damage": 31,
    "Precision": 18,
    "Recoil": 4,
    "Clip": 30,
    "FiringRate": 0.8,
    "ReloadDuration": 1,
    "Required": "123021,123025,122016",
    "quantity": "1,2,4",
    "Duration": 600,
    "output": 1
  },
  {
    "ID": "30803",
    "Type": 2,
    "Quality": 1,
    "Name": "M16A4",
    "AmmoType": 8,
    "PriceFluctuation": 0.0574083545586173,
    "Damage": 34,
    "Precision": 17,
    "Recoil": 4,
    "Clip": 20,
    "FiringRate": 0.7,
    "ReloadDuration": 1,
    "Required": "123021,123025,122016",
    "quantity": "1,1,4",
    "Duration": 10,
    "output": 1
  },
  {
    "ID": "30804",
    "Type": 2,
    "Quality": 3,
    "Name": "AUG",
    "AmmoType": 8,
    "PriceFluctuation": 0.07632619087799,
    "Damage": 33,
    "Precision": 17,
    "Recoil": 4,
    "Clip": 30,
    "FiringRate": 0.7,
    "ReloadDuration": 1,
    "Required": "123021,123025,122016",
    "quantity": "1,2,4",
    "Duration": 360,
    "output": 1
  },
  {
    "ID": "30901",
    "Type": 2,
    "Quality": 4,
    "Name": "M7",
    "AmmoType": 9,
    "PriceFluctuation": 0.0829023594251229,
    "Damage": 37,
    "Precision": 18,
    "Recoil": 4,
    "Clip": 30,
    "FiringRate": 0.8,
    "ReloadDuration": 1,
    "Required": "123021,123025,122016",
    "quantity": "1,1,3",
    "Duration": 600,
    "output": 1
  },
  {
    "ID": "30805",
    "Type": 2,
    "Quality": 2,
    "Name": "SG552",
    "AmmoType": 8,
    "PriceFluctuation": 0.0741569641419737,
    "Damage": 19,
    "Precision": 21,
    "Recoil": 6,
    "Clip": 30,
    "FiringRate": 1.1,
    "ReloadDuration": 1,
    "Required": "123021,123025,122016",
    "quantity": "1,2,4",
    "Duration": 120,
    "output": 1
  },
  {
    "ID": "30702",
    "Type": 2,
    "Quality": 3,
    "Name": "AK-12",
    "AmmoType": 7,
    "PriceFluctuation": 0.0638716365107909,
    "Damage": 29,
    "Precision": 20,
    "Recoil": 5,
    "Clip": 30,
    "FiringRate": 1,
    "ReloadDuration": 1,
    "Required": "123021,123025,122016",
    "quantity": "1,1,4",
    "Duration": 360,
    "output": 1
  },
  {
    "ID": "31101",
    "Type": 2,
    "Quality": 3,
    "Name": "SCAR-H",
    "AmmoType": 11,
    "PriceFluctuation": 0.0928053179448843,
    "Damage": 37,
    "Precision": 18,
    "Recoil": 4,
    "Clip": 20,
    "FiringRate": 0.8,
    "ReloadDuration": 1,
    "Required": "123021,123025,122016",
    "quantity": "1,2,4",
    "Duration": 360,
    "output": 1
  },
  {
    "ID": "31102",
    "Type": 2,
    "Quality": 2,
    "Name": "G3",
    "AmmoType": 11,
    "PriceFluctuation": 0.0566851909659903,
    "Damage": 38,
    "Precision": 16,
    "Recoil": 3,
    "Clip": 20,
    "FiringRate": 0.6,
    "ReloadDuration": 1,
    "Required": "123021,123025,122016",
    "quantity": "1,1,3",
    "Duration": 120,
    "output": 1
  },
  {
    "ID": "31002",
    "Type": 2,
    "Quality": 2,
    "Name": "PTR-32",
    "AmmoType": 10,
    "PriceFluctuation": 0.0786154365505705,
    "Damage": 36,
    "Precision": 17,
    "Recoil": 4,
    "Clip": 30,
    "FiringRate": 0.7,
    "ReloadDuration": 1,
    "Required": "123021,123025,122016",
    "quantity": "1,2,4",
    "Duration": 120,
    "output": 1
  },
  {
    "ID": "30806",
    "Type": 2,
    "Quality": 1,
    "Name": "CAR-15",
    "AmmoType": 8,
    "PriceFluctuation": 0.0746260407872422,
    "Damage": 26,
    "Precision": 17,
    "Recoil": 4,
    "Clip": 30,
    "FiringRate": 0.7,
    "ReloadDuration": 1,
    "Required": "123021,123025,122016",
    "quantity": "1,1,4",
    "Duration": 10,
    "output": 1
  },
  {
    "ID": "31402",
    "Type": 2,
    "Quality": 4,
    "Name": "ASVal",
    "AmmoType": 14,
    "PriceFluctuation": 0.0955777809421354,
    "Damage": 34,
    "Precision": 19,
    "Recoil": 5,
    "Clip": 20,
    "FiringRate": 0.9,
    "ReloadDuration": 1,
    "Required": "123021,123025,122016",
    "quantity": "1,2,4",
    "Duration": 600,
    "output": 1
  },
  {
    "ID": "30602",
    "Type": 2,
    "Quality": 3,
    "Name": "腾龙",
    "AmmoType": 6,
    "PriceFluctuation": 0.0585347549924765,
    "Damage": 37,
    "Precision": 17,
    "Recoil": 4,
    "Clip": 30,
    "FiringRate": 0.7,
    "ReloadDuration": 1,
    "Required": "123021,123025,122016",
    "quantity": "1,1,3",
    "Duration": 360,
    "output": 1
  },
  {
    "ID": "31201",
    "Type": 5,
    "Quality": 2,
    "Name": "SV-98",
    "AmmoType": 12,
    "PriceFluctuation": 0.0694890488912945,
    "Damage": 72,
    "Precision": 11,
    "Recoil": 1,
    "Clip": 5,
    "FiringRate": 0.1,
    "ReloadDuration": 1,
    "Required": "123021,123025,122016",
    "quantity": "1,2,4",
    "Duration": 120,
    "output": 1
  },
  {
    "ID": "31103",
    "Type": 5,
    "Quality": 2,
    "Name": "R93",
    "AmmoType": 11,
    "PriceFluctuation": 0.0864754488321123,
    "Damage": 73,
    "Precision": 11,
    "Recoil": 1,
    "Clip": 5,
    "FiringRate": 0.1,
    "ReloadDuration": 1,
    "Required": "123021,123025,122016",
    "quantity": "1,1,4",
    "Duration": 120,
    "output": 1
  },
  {
    "ID": "31104",
    "Type": 5,
    "Quality": 3,
    "Name": "M700",
    "AmmoType": 11,
    "PriceFluctuation": 0.0716774609777851,
    "Damage": 70,
    "Precision": 11,
    "Recoil": 1,
    "Clip": 5,
    "FiringRate": 0.1,
    "ReloadDuration": 1,
    "Required": "123021,123025,122016",
    "quantity": "1,2,4",
    "Duration": 360,
    "output": 1
  },
  {
    "ID": "31701",
    "Type": 5,
    "Quality": 5,
    "Name": "AWM",
    "AmmoType": 17,
    "PriceFluctuation": 0.0599758158318539,
    "Damage": 70,
    "Precision": 11,
    "Recoil": 1,
    "Clip": 5,
    "FiringRate": 0.1,
    "ReloadDuration": 1,
    "Required": "123021,123025,122016",
    "quantity": "1,1,3",
    "Duration": 600,
    "output": 1
  },
  {
    "ID": "31105",
    "Type": 4,
    "Quality": 1,
    "Name": "SR9",
    "AmmoType": 11,
    "PriceFluctuation": 0.0576010259721219,
    "Damage": 56,
    "Precision": 12,
    "Recoil": 1,
    "Clip": 10,
    "FiringRate": 0.2,
    "ReloadDuration": 1,
    "Required": "123021,123025,122016",
    "quantity": "1,2,4",
    "Duration": 10,
    "output": 1
  },
  {
    "ID": "30807",
    "Type": 4,
    "Quality": 2,
    "Name": "Mini14",
    "AmmoType": 8,
    "PriceFluctuation": 0.0825929849247857,
    "Damage": 57,
    "Precision": 12,
    "Recoil": 1,
    "Clip": 10,
    "FiringRate": 0.2,
    "ReloadDuration": 1,
    "Required": "123021,123025,122016",
    "quantity": "1,1,4",
    "Duration": 120,
    "output": 1
  },
  {
    "ID": "31403",
    "Type": 4,
    "Quality": 2,
    "Name": "VSS",
    "AmmoType": 14,
    "PriceFluctuation": 0.060713422981212,
    "Damage": 55,
    "Precision": 15,
    "Recoil": 3,
    "Clip": 20,
    "FiringRate": 0.5,
    "ReloadDuration": 1,
    "Required": "123021,123025,122016",
    "quantity": "1,2,4",
    "Duration": 120,
    "output": 1
  },
  {
    "ID": "31202",
    "Type": 4,
    "Quality": 3,
    "Name": "SVD",
    "AmmoType": 12,
    "PriceFluctuation": 0.0747736033258433,
    "Damage": 57,
    "Precision": 12,
    "Recoil": 1,
    "Clip": 10,
    "FiringRate": 0.2,
    "ReloadDuration": 1,
    "Required": "123021,123025,122016",
    "quantity": "1,1,3",
    "Duration": 360,
    "output": 1
  },
  {
    "ID": "31106",
    "Type": 4,
    "Quality": 3,
    "Name": "M14",
    "AmmoType": 11,
    "PriceFluctuation": 0.0751903460191834,
    "Damage": 53,
    "Precision": 15,
    "Recoil": 3,
    "Clip": 20,
    "FiringRate": 0.5,
    "ReloadDuration": 1,
    "Required": "123021,123025,122016",
    "quantity": "1,2,4",
    "Duration": 360,
    "output": 1
  },
  {
    "ID": "31003",
    "Type": 4,
    "Quality": 3,
    "Name": "SKS",
    "AmmoType": 10,
    "PriceFluctuation": 0.097037968862931,
    "Damage": 57,
    "Precision": 12,
    "Recoil": 1,
    "Clip": 10,
    "FiringRate": 0.2,
    "ReloadDuration": 1,
    "Required": "123021,123025,122016",
    "quantity": "1,1,4",
    "Duration": 360,
    "output": 1
  },
  {
    "ID": "31107",
    "Type": 4,
    "Quality": 4,
    "Name": "SR-25",
    "AmmoType": 11,
    "PriceFluctuation": 0.0560211259803435,
    "Damage": 52,
    "Precision": 12,
    "Recoil": 1,
    "Clip": 10,
    "FiringRate": 0.2,
    "ReloadDuration": 1,
    "Required": "123021,123025,122016",
    "quantity": "1,2,4",
    "Duration": 600,
    "output": 1
  },
  {
    "ID": "31108",
    "Type": 4,
    "Quality": 3,
    "Name": "PSG-1",
    "AmmoType": 11,
    "PriceFluctuation": 0.0967107451154334,
    "Damage": 54,
    "Precision": 12,
    "Recoil": 1,
    "Clip": 10,
    "FiringRate": 0.2,
    "ReloadDuration": 1,
    "Required": "123021,123025,122016",
    "quantity": "1,1,3",
    "Duration": 360,
    "output": 1
  },
  {
    "ID": "30603",
    "Type": 6,
    "Quality": 4,
    "Name": "QJB201",
    "AmmoType": 6,
    "PriceFluctuation": 0.0534039209271286,
    "Damage": 33,
    "Precision": 17,
    "Recoil": 4,
    "Clip": 75,
    "FiringRate": 0.7,
    "ReloadDuration": 1,
    "Required": "123021,123025,122016",
    "quantity": "1,2,4",
    "Duration": 600,
    "output": 1
  },
  {
    "ID": "31203",
    "Type": 6,
    "Quality": 3,
    "Name": "PKM",
    "AmmoType": 12,
    "PriceFluctuation": 0.069327091712389,
    "Damage": 35,
    "Precision": 17,
    "Recoil": 4,
    "Clip": 75,
    "FiringRate": 0.7,
    "ReloadDuration": 1,
    "Required": "123021,123025,122016",
    "quantity": "1,1,4",
    "Duration": 360,
    "output": 1
  },
  {
    "ID": "30808",
    "Type": 6,
    "Quality": 3,
    "Name": "M249",
    "AmmoType": 8,
    "PriceFluctuation": 0.0871275586817778,
    "Damage": 34,
    "Precision": 18,
    "Recoil": 4,
    "Clip": 100,
    "FiringRate": 0.8,
    "ReloadDuration": 1,
    "Required": "123021,123025,122016",
    "quantity": "1,2,4",
    "Duration": 360,
    "output": 1
  },
  {
    "ID": "30902",
    "Type": 6,
    "Quality": 4,
    "Name": "M250",
    "AmmoType": 9,
    "PriceFluctuation": 0.0580934384985004,
    "Damage": 33,
    "Precision": 16,
    "Recoil": 3,
    "Clip": 75,
    "FiringRate": 0.6,
    "ReloadDuration": 1,
    "Required": "123021,123025,122016",
    "quantity": "1,1,3",
    "Duration": 600,
    "output": 1
  },
  {
    "ID": "31601",
    "Type": 7,
    "Quality": 2,
    "Name": "M1014",
    "AmmoType": 16,
    "PriceFluctuation": 0.0687150041988155,
    "Damage": 19,
    "Precision": 13,
    "Recoil": 2,
    "Clip": 7,
    "FiringRate": 0.3,
    "ReloadDuration": 1,
    "Required": "123021,123025,122016",
    "quantity": "1,2,4",
    "Duration": 120,
    "output": 1
  },
  {
    "ID": "31602",
    "Type": 7,
    "Quality": 2,
    "Name": "S12K",
    "AmmoType": 16,
    "PriceFluctuation": 0.073506929273652,
    "Damage": 18,
    "Precision": 15,
    "Recoil": 3,
    "Clip": 24,
    "FiringRate": 0.5,
    "ReloadDuration": 1,
    "Required": "123021,123025,122016",
    "quantity": "1,1,4",
    "Duration": 120,
    "output": 1
  },
  {
    "ID": "31603",
    "Type": 7,
    "Quality": 1,
    "Name": "M870",
    "AmmoType": 16,
    "PriceFluctuation": 0.0787023368405663,
    "Damage": 18,
    "Precision": 12,
    "Recoil": 1,
    "Clip": 2,
    "FiringRate": 0.2,
    "ReloadDuration": 1,
    "Required": "123021,123025,122016",
    "quantity": "1,2,4",
    "Duration": 10,
    "output": 1
  }
]