[
    {
        "day": 1,
        "takeoutOrders": [
            {
                "id": "day1_order1",
                "avatarName": "上班族",
                "customerName": "小明",
                "showTime": [
                    8,
                    30
                ],
                "expireTime": [
                    10,
                    0
                ],
                "content": "经典冷面",
                "remark": "一份冷面皮，刷上油，放两个鸡蛋，加点点浅色酱，加一片生菜和一点点洋葱就行",
                "order": {
                    "冷面皮": {
                        "type": "撒料类",
                        "need": 1,
                        "count": 1
                    },
                    "鸡蛋": {
                        "type": "撒料类",
                        "need": 1,
                        "count": 2
                    },
                    "油": {
                        "type": "撒料类",
                        "need": 1,
                        "count": 1
                    },
                    "洋葱": {
                        "type": "撒料类",
                        "need": 1,
                        "count": 1
                    },
                    "浅色酱": {
                        "type": "撒料类",
                        "need": 1,
                        "count": 1
                    },
                    "生菜": {
                        "type": "撒料类",
                        "need": 1,
                        "count": 1
                    }
                }
            },
            {
                "id": "day1_order2",
                "avatarName": "上班族",
                "customerName": "小红",
                "showTime": [
                    9,
                    15
                ],
                "expireTime": [
                    9,
                    45
                ],
                "content": "标准冷面",
                "remark": "一份冷面皮，刷上油，放两个鸡蛋，加点点浅色酱，加一片生菜和一点点洋葱就行",
                "order": {
                    "冷面皮": {
                        "type": "撒料类",
                        "need": 1,
                        "count": 1
                    },
                    "鸡蛋": {
                        "type": "撒料类",
                        "need": 1,
                        "count": 2
                    },
                    "油": {
                        "type": "撒料类",
                        "need": 1,
                        "count": 1
                    },
                    "洋葱": {
                        "type": "撒料类",
                        "need": 1,
                        "count": 1
                    },
                    "浅色酱": {
                        "type": "撒料类",
                        "need": 1,
                        "count": 1
                    },
                    "生菜": {
                        "type": "撒料类",
                        "need": 1,
                        "count": 1
                    }
                }
            },
            {
                "id": "day1_order3",
                "avatarName": "上班族",
                "customerName": "小李",
                "showTime": [
                    10,
                    30
                ],
                "expireTime": [
                    11,
                    0
                ],
                "content": "豪华冷面",
                "remark": "冷面皮一份，刷上油，三个鸡蛋，抹花生酱，一片洋葱、三片生菜、一块猪排，再放根辣条",
                "order": {
                    "冷面皮": {
                        "type": "撒料类",
                        "need": 1,
                        "count": 1
                    },
                    "鸡蛋": {
                        "type": "撒料类",
                        "need": 1,
                        "count": 3
                    },
                    "油": {
                        "type": "撒料类",
                        "need": 1,
                        "count": 1
                    },
                    "洋葱": {
                        "type": "撒料类",
                        "need": 1,
                        "count": 1
                    },
                    "花生酱": {
                        "type": "撒料类",
                        "need": 1,
                        "count": 1
                    },
                    "生菜": {
                        "type": "撒料类",
                        "need": 1,
                        "count": 3
                    },
                    "猪排": {
                        "type": "撒料类",
                        "need": 1,
                        "count": 1
                    },
                    "辣条": {
                        "type": "撒料类",
                        "need": 1,
                        "count": 1
                    }
                }
            },
            {
                "id": "day1_order4",
                "avatarName": "上班族",
                "customerName": "小王",
                "showTime": [
                    14,
                    0
                ],
                "expireTime": [
                    14,
                    30
                ],
                "content": "辣味冷面",
                "remark": "冷面皮一份刷油，两个鸡蛋，抹花生酱，一片洋葱、一片生菜、两块鸡柳，再来点辣白菜和辣条",
                "order": {
                    "冷面皮": {
                        "type": "撒料类",
                        "need": 1,
                        "count": 1
                    },
                    "鸡蛋": {
                        "type": "撒料类",
                        "need": 1,
                        "count": 2
                    },
                    "油": {
                        "type": "撒料类",
                        "need": 1,
                        "count": 1
                    },
                    "洋葱": {
                        "type": "撒料类",
                        "need": 1,
                        "count": 1
                    },
                    "花生酱": {
                        "type": "撒料类",
                        "need": 1,
                        "count": 1
                    },
                    "生菜": {
                        "type": "撒料类",
                        "need": 1,
                        "count": 1
                    },
                    "鸡柳": {
                        "type": "撒料类",
                        "need": 1,
                        "count": 2
                    },
                    "辣白菜": {
                        "type": "撒料类",
                        "need": 1,
                        "count": 1
                    },
                    "辣条": {
                        "type": "撒料类",
                        "need": 1,
                        "count": 1
                    }
                }
            },
            {
                "id": "day1_order5",
                "avatarName": "上班族",
                "customerName": "小张",
                "showTime": [
                    16,
                    15
                ],
                "expireTime": [
                    16,
                    45
                ],
                "content": "豪华鸡蛋冷面",
                "remark": "冷面皮一份刷油，5个鸡蛋，一点洋葱",
                "order": {
                    "冷面皮": {
                        "type": "撒料类",
                        "need": 1,
                        "count": 1,
                        "percentage": 0,
                        "rotateCount": 0
                    },
                    "鸡蛋": {
                        "type": "撒料类",
                        "need": 1,
                        "count": 5,
                        "percentage": 0,
                        "rotateCount": 0
                    },
                    "洋葱": {
                        "type": "撒料类",
                        "need": 1,
                        "count": 1
                    }
                }
            }
        ]
    },
    {
        "day": 2,
        "takeoutOrders": [
            {
                "id": "day2_order1",
                "avatarName": "上班族",
                "customerName": "小陈",
                "showTime": [
                    8,
                    0
                ],
                "expireTime": [
                    9,
                    15
                ],
                "content": "葱花鸡蛋灌饼",
                "remark": "重口味",
                "order": {
                    "冷面皮": {
                        "type": "撒料类",
                        "need": 1,
                        "count": 2,
                        "percentage": 0,
                        "rotateCount": 0
                    },
                    "鸡蛋": {
                        "type": "撒料类",
                        "need": 1,
                        "count": 1,
                        "percentage": 0,
                        "rotateCount": 0
                    }
                }
            },
            {
                "id": "day2_order2",
                "avatarName": "上班族",
                "customerName": "小周",
                "showTime": [
                    9,
                    30
                ],
                "expireTime": [
                    10,
                    0
                ],
                "content": "豪华套餐",
                "remark": "全部配料都要",
                "order": {
                    "冷面皮": {
                        "type": "撒料类",
                        "need": 1,
                        "count": 2,
                        "percentage": 0,
                        "rotateCount": 0
                    },
                    "鸡蛋": {
                        "type": "撒料类",
                        "need": 1,
                        "count": 1,
                        "percentage": 0,
                        "rotateCount": 0
                    }
                }
            },
            {
                "id": "day2_order3",
                "avatarName": "上班族",
                "customerName": "小赵",
                "showTime": [
                    11,
                    0
                ],
                "expireTime": [
                    11,
                    30
                ],
                "content": "轻食鸡蛋灌饼",
                "remark": "少酱多菜",
                "order": {
                    "冷面皮": {
                        "type": "撒料类",
                        "need": 1,
                        "count": 2,
                        "percentage": 0,
                        "rotateCount": 0
                    },
                    "鸡蛋": {
                        "type": "撒料类",
                        "need": 1,
                        "count": 1,
                        "percentage": 0,
                        "rotateCount": 0
                    }
                }
            },
            {
                "id": "day2_order4",
                "avatarName": "上班族",
                "customerName": "小钱",
                "showTime": [
                    13,
                    30
                ],
                "expireTime": [
                    14,
                    0
                ],
                "content": "双蛋加脆",
                "remark": "两个鸡蛋加薄脆",
                "order": {
                    "冷面皮": {
                        "type": "撒料类",
                        "need": 1,
                        "count": 2,
                        "percentage": 0,
                        "rotateCount": 0
                    },
                    "鸡蛋": {
                        "type": "撒料类",
                        "need": 1,
                        "count": 1,
                        "percentage": 0,
                        "rotateCount": 0
                    }
                }
            },
            {
                "id": "day2_order5",
                "avatarName": "上班族",
                "customerName": "小孙",
                "showTime": [
                    15,
                    15
                ],
                "expireTime": [
                    15,
                    45
                ],
                "content": "传统鸡蛋灌饼",
                "remark": "经典口味",
                "order": {
                    "冷面皮": {
                        "type": "撒料类",
                        "need": 1,
                        "count": 2,
                        "percentage": 0,
                        "rotateCount": 0
                    },
                    "鸡蛋": {
                        "type": "撒料类",
                        "need": 1,
                        "count": 1,
                        "percentage": 0,
                        "rotateCount": 0
                    }
                }
            },
            {
                "id": "day2_order6",
                "avatarName": "上班族",
                "customerName": "小林",
                "showTime": [
                    17,
                    45
                ],
                "expireTime": [
                    18,
                    15
                ],
                "content": "超辣鸡蛋灌饼",
                "remark": "非常非常辣",
                "order": {
                    "冷面皮": {
                        "type": "撒料类",
                        "need": 1,
                        "count": 2,
                        "percentage": 0,
                        "rotateCount": 0
                    },
                    "鸡蛋": {
                        "type": "撒料类",
                        "need": 1,
                        "count": 1,
                        "percentage": 0,
                        "rotateCount": 0
                    }
                }
            }
        ]
    },
    {
        "day": 3,
        "takeoutOrders": [
            {
                "id": "day3_order1",
                "avatarName": "上班族",
                "customerName": "小美",
                "showTime": [
                    8,
                    15
                ],
                "expireTime": [
                    8,
                    45
                ],
                "content": "营养早餐",
                "remark": "多放鸡蛋",
                "order": {
                    "冷面皮": {
                        "type": "撒料类",
                        "need": 1,
                        "count": 2,
                        "percentage": 0,
                        "rotateCount": 0
                    },
                    "鸡蛋": {
                        "type": "撒料类",
                        "need": 1,
                        "count": 1,
                        "percentage": 0,
                        "rotateCount": 0
                    }
                }
            },
            {
                "id": "day3_order2",
                "avatarName": "上班族",
                "customerName": "小吴",
                "showTime": [
                    9,
                    45
                ],
                "expireTime": [
                    10,
                    15
                ],
                "content": "健康蔬菜灌饼",
                "remark": "多菜少酱",
                "order": {
                    "冷面皮": {
                        "type": "撒料类",
                        "need": 1,
                        "count": 2,
                        "percentage": 0,
                        "rotateCount": 0
                    },
                    "鸡蛋": {
                        "type": "撒料类",
                        "need": 1,
                        "count": 1,
                        "percentage": 0,
                        "rotateCount": 0
                    }
                }
            },
            {
                "id": "day3_order3",
                "avatarName": "上班族",
                "customerName": "小郑",
                "showTime": [
                    11,
                    30
                ],
                "expireTime": [
                    12,
                    0
                ],
                "content": "巨无霸鸡蛋灌饼",
                "remark": "加双倍材料",
                "order": {
                    "冷面皮": {
                        "type": "撒料类",
                        "need": 1,
                        "count": 2,
                        "percentage": 0,
                        "rotateCount": 0
                    },
                    "鸡蛋": {
                        "type": "撒料类",
                        "need": 1,
                        "count": 1,
                        "percentage": 0,
                        "rotateCount": 0
                    }
                }
            },
            {
                "id": "day3_order4",
                "avatarName": "上班族",
                "customerName": "小冯",
                "showTime": [
                    14,
                    30
                ],
                "expireTime": [
                    15,
                    0
                ],
                "content": "香脆鸡蛋灌饼",
                "remark": "多加薄脆",
                "order": {
                    "冷面皮": {
                        "type": "撒料类",
                        "need": 1,
                        "count": 2,
                        "percentage": 0,
                        "rotateCount": 0
                    },
                    "鸡蛋": {
                        "type": "撒料类",
                        "need": 1,
                        "count": 1,
                        "percentage": 0,
                        "rotateCount": 0
                    }
                }
            },
            {
                "id": "day3_order5",
                "avatarName": "上班族",
                "customerName": "小陈",
                "showTime": [
                    16,
                    0
                ],
                "expireTime": [
                    16,
                    30
                ],
                "content": "清爽版鸡蛋灌饼",
                "remark": "少油少盐",
                "order": {
                    "冷面皮": {
                        "type": "撒料类",
                        "need": 1,
                        "count": 2,
                        "percentage": 0,
                        "rotateCount": 0
                    },
                    "鸡蛋": {
                        "type": "撒料类",
                        "need": 1,
                        "count": 1,
                        "percentage": 0,
                        "rotateCount": 0
                    }
                }
            },
            {
                "id": "day3_order6",
                "avatarName": "上班族",
                "customerName": "小杨",
                "showTime": [
                    18,
                    0
                ],
                "expireTime": [
                    18,
                    30
                ],
                "content": "夜宵鸡蛋灌饼",
                "remark": "口味重一点",
                "order": {
                    "冷面皮": {
                        "type": "撒料类",
                        "need": 1,
                        "count": 2,
                        "percentage": 0,
                        "rotateCount": 0
                    },
                    "鸡蛋": {
                        "type": "撒料类",
                        "need": 1,
                        "count": 1,
                        "percentage": 0,
                        "rotateCount": 0
                    }
                }
            }
        ]
    },
    {
        "day": 5,
        "takeoutOrders": [
            {
                "id": "day5_order1",
                "avatarName": "上班族",
                "customerName": "小陈",
                "showTime": [
                    8,
                    30
                ],
                "expireTime": [
                    10,
                    30
                ],
                "content": "加蛋多料冷面，配经典酱料和多种配菜",
                "remark": "冷面皮一份刷油，2个鸡蛋，抹浅色酱，加2片洋葱、1片生菜、1根火腿肠和少许芝麻",
                "order": {
                    "冷面皮": {
                        "type": "撒料类",
                        "need": 1,
                        "count": 1
                    },
                    "鸡蛋": {
                        "type": "撒料类",
                        "need": 1,
                        "count": 2
                    },
                    "油": {
                        "type": "撒料类",
                        "need": 1,
                        "count": 1
                    },
                    "浅色酱": {
                        "type": "撒料类",
                        "need": 1,
                        "count": 1
                    },
                    "洋葱": {
                        "type": "撒料类",
                        "need": 1,
                        "count": 2
                    },
                    "生菜": {
                        "type": "撒料类",
                        "need": 1,
                        "count": 1
                    },
                    "火腿肠": {
                        "type": "撒料类",
                        "need": 1,
                        "count": 1
                    },
                    "芝麻": {
                        "type": "撒料类",
                        "need": 1,
                        "count": 1
                    }
                }
            },
            {
                "id": "day5_order2",
                "avatarName": "便衣",
                "customerName": "老李",
                "showTime": [
                    9,
                    15
                ],
                "expireTime": [
                    11,
                    15
                ],
                "content": "多蛋饱腹冷面，配辣白菜和调味酱",
                "remark": "冷面皮一份刷油，3个鸡蛋，抹调味酱，加1片洋葱、2片生菜、1份辣白菜和1根鸡柳",
                "order": {
                    "冷面皮": {
                        "type": "撒料类",
                        "need": 1,
                        "count": 1
                    },
                    "鸡蛋": {
                        "type": "撒料类",
                        "need": 1,
                        "count": 3
                    },
                    "油": {
                        "type": "撒料类",
                        "need": 1,
                        "count": 1
                    },
                    "调味酱": {
                        "type": "撒料类",
                        "need": 1,
                        "count": 1
                    },
                    "洋葱": {
                        "type": "撒料类",
                        "need": 1,
                        "count": 1
                    },
                    "生菜": {
                        "type": "撒料类",
                        "need": 1,
                        "count": 2
                    },
                    "辣白菜": {
                        "type": "撒料类",
                        "need": 1,
                        "count": 1
                    },
                    "鸡柳": {
                        "type": "撒料类",
                        "need": 1,
                        "count": 1
                    }
                }
            },
            {
                "id": "day5_order3",
                "avatarName": "学生",
                "customerName": "小林",
                "showTime": [
                    10,
                    0
                ],
                "expireTime": [
                    12,
                    0
                ],
                "content": "实惠多料冷面，加辣条和鸡柳",
                "remark": "冷面皮一份刷油，1个鸡蛋，抹调味酱，加1片生菜、1根火腿肠、1份辣条和1根鸡柳",
                "order": {
                    "冷面皮": {
                        "type": "撒料类",
                        "need": 1,
                        "count": 1
                    },
                    "鸡蛋": {
                        "type": "撒料类",
                        "need": 1,
                        "count": 1
                    },
                    "油": {
                        "type": "撒料类",
                        "need": 1,
                        "count": 1
                    },
                    "调味酱": {
                        "type": "撒料类",
                        "need": 1,
                        "count": 1
                    },
                    "生菜": {
                        "type": "撒料类",
                        "need": 1,
                        "count": 1
                    },
                    "火腿肠": {
                        "type": "撒料类",
                        "need": 1,
                        "count": 1
                    },
                    "辣条": {
                        "type": "撒料类",
                        "need": 1,
                        "count": 1
                    },
                    "鸡柳": {
                        "type": "撒料类",
                        "need": 1,
                        "count": 1
                    }
                }
            },
            {
                "id": "day5_order4",
                "avatarName": "美女",
                "customerName": "小苏",
                "showTime": [
                    11,
                    45
                ],
                "expireTime": [
                    13,
                    45
                ],
                "content": "清爽营养冷面，配芝士和鱼片",
                "remark": "冷面皮一份刷油，1个鸡蛋，抹浅色酱，加2片生菜、1片芝士、1份鱼片和少许芝麻",
                "order": {
                    "冷面皮": {
                        "type": "撒料类",
                        "need": 1,
                        "count": 1
                    },
                    "鸡蛋": {
                        "type": "撒料类",
                        "need": 1,
                        "count": 1
                    },
                    "油": {
                        "type": "撒料类",
                        "need": 1,
                        "count": 1
                    },
                    "浅色酱": {
                        "type": "撒料类",
                        "need": 1,
                        "count": 1
                    },
                    "生菜": {
                        "type": "撒料类",
                        "need": 1,
                        "count": 2
                    },
                    "芝士": {
                        "type": "撒料类",
                        "need": 1,
                        "count": 1
                    },
                    "鱼片": {
                        "type": "撒料类",
                        "need": 1,
                        "count": 1
                    },
                    "芝麻": {
                        "type": "撒料类",
                        "need": 1,
                        "count": 1
                    }
                }
            },
            {
                "id": "day5_order5",
                "avatarName": "体育",
                "customerName": "小青",
                "showTime": [
                    13,
                    30
                ],
                "expireTime": [
                    15,
                    30
                ],
                "content": "高蛋白能量冷面，加猪排和多蛋",
                "remark": "冷面皮一份刷油，3个鸡蛋，抹花生酱，加2片生菜、1块猪排、1根鸡柳和1份辣白菜",
                "order": {
                    "冷面皮": {
                        "type": "撒料类",
                        "need": 1,
                        "count": 1
                    },
                    "鸡蛋": {
                        "type": "撒料类",
                        "need": 1,
                        "count": 3
                    },
                    "油": {
                        "type": "撒料类",
                        "need": 1,
                        "count": 1
                    },
                    "花生酱": {
                        "type": "撒料类",
                        "need": 1,
                        "count": 1
                    },
                    "生菜": {
                        "type": "撒料类",
                        "need": 1,
                        "count": 2
                    },
                    "猪排": {
                        "type": "撒料类",
                        "need": 1,
                        "count": 1
                    },
                    "鸡柳": {
                        "type": "撒料类",
                        "need": 1,
                        "count": 1
                    },
                    "辣白菜": {
                        "type": "撒料类",
                        "need": 1,
                        "count": 1
                    }
                }
            },
            {
                "id": "day5_order6",
                "avatarName": "包租婆",
                "customerName": "小红",
                "showTime": [
                    14,
                    20
                ],
                "expireTime": [
                    16,
                    20
                ],
                "content": "豪华加料冷面，配多种酱料和配菜",
                "remark": "冷面皮一份刷油，2个鸡蛋，抹花生酱和浅色酱，加2片洋葱、1片生菜、1根火腿肠和1份芝麻",
                "order": {
                    "冷面皮": {
                        "type": "撒料类",
                        "need": 1,
                        "count": 1
                    },
                    "鸡蛋": {
                        "type": "撒料类",
                        "need": 1,
                        "count": 2
                    },
                    "油": {
                        "type": "撒料类",
                        "need": 1,
                        "count": 1
                    },
                    "花生酱": {
                        "type": "撒料类",
                        "need": 1,
                        "count": 1
                    },
                    "浅色酱": {
                        "type": "撒料类",
                        "need": 1,
                        "count": 1
                    },
                    "洋葱": {
                        "type": "撒料类",
                        "need": 1,
                        "count": 2
                    },
                    "生菜": {
                        "type": "撒料类",
                        "need": 1,
                        "count": 1
                    },
                    "火腿肠": {
                        "type": "撒料类",
                        "need": 1,
                        "count": 1
                    },
                    "芝麻": {
                        "type": "撒料类",
                        "need": 1,
                        "count": 1
                    }
                }
            },
            {
                "id": "day5_order7",
                "avatarName": "非主流",
                "customerName": "小蓝",
                "showTime": [
                    16,
                    0
                ],
                "expireTime": [
                    18,
                    0
                ],
                "content": "个性混搭冷面，加辣条和芝士",
                "remark": "冷面皮一份刷油，2个鸡蛋，抹调味酱，加1片洋葱、1片生菜、1份辣条、1片芝士和1根火腿肠",
                "order": {
                    "冷面皮": {
                        "type": "撒料类",
                        "need": 1,
                        "count": 1
                    },
                    "鸡蛋": {
                        "type": "撒料类",
                        "need": 1,
                        "count": 2
                    },
                    "油": {
                        "type": "撒料类",
                        "need": 1,
                        "count": 1
                    },
                    "调味酱": {
                        "type": "撒料类",
                        "need": 1,
                        "count": 1
                    },
                    "洋葱": {
                        "type": "撒料类",
                        "need": 1,
                        "count": 1
                    },
                    "生菜": {
                        "type": "撒料类",
                        "need": 1,
                        "count": 1
                    },
                    "辣条": {
                        "type": "撒料类",
                        "need": 1,
                        "count": 1
                    },
                    "芝士": {
                        "type": "撒料类",
                        "need": 1,
                        "count": 1
                    },
                    "火腿肠": {
                        "type": "撒料类",
                        "need": 1,
                        "count": 1
                    }
                }
            },
            {
                "id": "day5_order1",
                "avatarName": "上班族",
                "customerName": "小陈",
                "showTime": [
                    8,
                    15
                ],
                "expireTime": [
                    8,
                    45
                ],
                "content": "加蛋加肠冷面，多酱多菜",
                "remark": "冷面皮一份刷油，两个鸡蛋煎熟，抹调味酱，加两片洋葱、四片生菜、一根火腿肠、一点辣白菜和少许芝麻",
                "order": {
                    "冷面皮": {
                        "type": "撒料类",
                        "need": 1,
                        "count": 1
                    },
                    "鸡蛋": {
                        "type": "撒料类",
                        "need": 1,
                        "count": 2
                    },
                    "油": {
                        "type": "撒料类",
                        "need": 1,
                        "count": 1
                    },
                    "洋葱": {
                        "type": "撒料类",
                        "need": 1,
                        "count": 2
                    },
                    "调味酱": {
                        "type": "撒料类",
                        "need": 1,
                        "count": 1
                    },
                    "生菜": {
                        "type": "撒料类",
                        "need": 1,
                        "count": 4
                    },
                    "火腿肠": {
                        "type": "撒料类",
                        "need": 1,
                        "count": 1
                    },
                    "辣白菜": {
                        "type": "撒料类",
                        "need": 1,
                        "count": 1
                    },
                    "芝麻": {
                        "type": "撒料类",
                        "need": 1,
                        "count": 1
                    }
                }
            },
            {
                "id": "day5_order2",
                "avatarName": "便衣",
                "customerName": "老李",
                "showTime": [
                    9,
                    0
                ],
                "expireTime": [
                    9,
                    30
                ],
                "content": "经典多蛋冷面，配猪排生菜",
                "remark": "冷面皮一份刷油，三个鸡蛋搅匀，抹浅色酱，加一片洋葱、三片生菜、一块猪排、少许辣条和一点芝麻",
                "order": {
                    "冷面皮": {
                        "type": "撒料类",
                        "need": 1,
                        "count": 1
                    },
                    "鸡蛋": {
                        "type": "撒料类",
                        "need": 1,
                        "count": 3
                    },
                    "油": {
                        "type": "撒料类",
                        "need": 1,
                        "count": 1
                    },
                    "洋葱": {
                        "type": "撒料类",
                        "need": 1,
                        "count": 1
                    },
                    "浅色酱": {
                        "type": "撒料类",
                        "need": 1,
                        "count": 1
                    },
                    "生菜": {
                        "type": "撒料类",
                        "need": 1,
                        "count": 3
                    },
                    "猪排": {
                        "type": "撒料类",
                        "need": 1,
                        "count": 1
                    },
                    "辣条": {
                        "type": "撒料类",
                        "need": 1,
                        "count": 1
                    },
                    "芝麻": {
                        "type": "撒料类",
                        "need": 1,
                        "count": 1
                    }
                }
            },
            {
                "id": "day5_order3",
                "avatarName": "学生",
                "customerName": "小林",
                "showTime": [
                    10,
                    20
                ],
                "expireTime": [
                    10,
                    50
                ],
                "content": "实惠饱肚冷面，多鸡柳辣条",
                "remark": "冷面皮一份刷油，一个鸡蛋打散，抹花生酱，加一片洋葱、两片生菜、两根鸡柳、两小包辣条和一点辣白菜",
                "order": {
                    "冷面皮": {
                        "type": "撒料类",
                        "need": 1,
                        "count": 1
                    },
                    "鸡蛋": {
                        "type": "撒料类",
                        "need": 1,
                        "count": 1
                    },
                    "油": {
                        "type": "撒料类",
                        "need": 1,
                        "count": 1
                    },
                    "洋葱": {
                        "type": "撒料类",
                        "need": 1,
                        "count": 1
                    },
                    "花生酱": {
                        "type": "撒料类",
                        "need": 1,
                        "count": 1
                    },
                    "生菜": {
                        "type": "撒料类",
                        "need": 1,
                        "count": 2
                    },
                    "鸡柳": {
                        "type": "撒料类",
                        "need": 1,
                        "count": 2
                    },
                    "辣条": {
                        "type": "撒料类",
                        "need": 1,
                        "count": 2
                    },
                    "辣白菜": {
                        "type": "撒料类",
                        "need": 1,
                        "count": 1
                    }
                }
            },
            {
                "id": "day5_order4",
                "avatarName": "美女",
                "customerName": "小苏",
                "showTime": [
                    11,
                    10
                ],
                "expireTime": [
                    11,
                    40
                ],
                "content": "清爽低卡冷面，少料多菜",
                "remark": "冷面皮一份刷油，两个鸡蛋溏心，抹浅色酱，加半片洋葱、五片生菜、少许鱼片、一点芝士和几粒芝麻",
                "order": {
                    "冷面皮": {
                        "type": "撒料类",
                        "need": 1,
                        "count": 1
                    },
                    "鸡蛋": {
                        "type": "撒料类",
                        "need": 1,
                        "count": 2
                    },
                    "油": {
                        "type": "撒料类",
                        "need": 1,
                        "count": 1
                    },
                    "洋葱": {
                        "type": "撒料类",
                        "need": 1,
                        "count": 1
                    },
                    "浅色酱": {
                        "type": "撒料类",
                        "need": 1,
                        "count": 1
                    },
                    "生菜": {
                        "type": "撒料类",
                        "need": 1,
                        "count": 5
                    },
                    "鱼片": {
                        "type": "撒料类",
                        "need": 1,
                        "count": 1
                    },
                    "芝士": {
                        "type": "撒料类",
                        "need": 1,
                        "count": 1
                    },
                    "芝麻": {
                        "type": "撒料类",
                        "need": 1,
                        "count": 1
                    }
                }
            },
            {
                "id": "day5_order5",
                "avatarName": "体育",
                "customerName": "小青",
                "showTime": [
                    12,
                    30
                ],
                "expireTime": [
                    13,
                    0
                ],
                "content": "能量加满冷面，多蛋多肉",
                "remark": "冷面皮一份刷油，四个鸡蛋全熟，抹花生酱，加三片洋葱、四片生菜、两块猪排、两根火腿肠和少许鸡柳",
                "order": {
                    "冷面皮": {
                        "type": "撒料类",
                        "need": 1,
                        "count": 1
                    },
                    "鸡蛋": {
                        "type": "撒料类",
                        "need": 1,
                        "count": 4
                    },
                    "油": {
                        "type": "撒料类",
                        "need": 1,
                        "count": 1
                    },
                    "洋葱": {
                        "type": "撒料类",
                        "need": 1,
                        "count": 3
                    },
                    "花生酱": {
                        "type": "撒料类",
                        "need": 1,
                        "count": 1
                    },
                    "生菜": {
                        "type": "撒料类",
                        "need": 1,
                        "count": 4
                    },
                    "猪排": {
                        "type": "撒料类",
                        "need": 1,
                        "count": 2
                    },
                    "火腿肠": {
                        "type": "撒料类",
                        "need": 1,
                        "count": 2
                    },
                    "鸡柳": {
                        "type": "撒料类",
                        "need": 1,
                        "count": 1
                    }
                }
            },
            {
                "id": "day5_order6",
                "avatarName": "包租婆",
                "customerName": "小红",
                "showTime": [
                    14,
                    20
                ],
                "expireTime": [
                    14,
                    50
                ],
                "content": "豪华顶配冷面，料足味全",
                "remark": "冷面皮一份刷油，三个鸡蛋煎香，抹调味酱加花生酱，加两片洋葱、三片生菜、一块猪排、一根火腿肠、一点辣白菜和少许芝麻",
                "order": {
                    "冷面皮": {
                        "type": "撒料类",
                        "need": 1,
                        "count": 1
                    },
                    "鸡蛋": {
                        "type": "撒料类",
                        "need": 1,
                        "count": 3
                    },
                    "油": {
                        "type": "撒料类",
                        "need": 1,
                        "count": 1
                    },
                    "洋葱": {
                        "type": "撒料类",
                        "need": 1,
                        "count": 2
                    },
                    "调味酱": {
                        "type": "撒料类",
                        "need": 1,
                        "count": 1
                    },
                    "花生酱": {
                        "type": "撒料类",
                        "need": 1,
                        "count": 1
                    },
                    "生菜": {
                        "type": "撒料类",
                        "need": 1,
                        "count": 3
                    },
                    "猪排": {
                        "type": "撒料类",
                        "need": 1,
                        "count": 1
                    },
                    "火腿肠": {
                        "type": "撒料类",
                        "need": 1,
                        "count": 1
                    },
                    "辣白菜": {
                        "type": "撒料类",
                        "need": 1,
                        "count": 1
                    },
                    "芝麻": {
                        "type": "撒料类",
                        "need": 1,
                        "count": 1
                    }
                }
            },
            {
                "id": "day5_order7",
                "avatarName": "非主流",
                "customerName": "小蓝",
                "showTime": [
                    16,
                    10
                ],
                "expireTime": [
                    16,
                    40
                ],
                "content": "混搭个性冷面，重口多料",
                "remark": "冷面皮一份刷油，两个鸡蛋双面煎，抹调味酱加辣条碎，加一片洋葱、两片生菜、一块芝士、少许鱼片、一根鸡柳和一点辣白菜",
                "order": {
                    "冷面皮": {
                        "type": "撒料类",
                        "need": 1,
                        "count": 1
                    },
                    "鸡蛋": {
                        "type": "撒料类",
                        "need": 1,
                        "count": 2
                    },
                    "油": {
                        "type": "撒料类",
                        "need": 1,
                        "count": 1
                    },
                    "洋葱": {
                        "type": "撒料类",
                        "need": 1,
                        "count": 1
                    },
                    "调味酱": {
                        "type": "撒料类",
                        "need": 1,
                        "count": 1
                    },
                    "生菜": {
                        "type": "撒料类",
                        "need": 1,
                        "count": 2
                    },
                    "芝士": {
                        "type": "撒料类",
                        "need": 1,
                        "count": 1
                    },
                    "鱼片": {
                        "type": "撒料类",
                        "need": 1,
                        "count": 1
                    },
                    "鸡柳": {
                        "type": "撒料类",
                        "need": 1,
                        "count": 1
                    },
                    "辣条": {
                        "type": "撒料类",
                        "need": 1,
                        "count": 1
                    },
                    "辣白菜": {
                        "type": "撒料类",
                        "need": 1,
                        "count": 1
                    }
                }
            },
            {
                "id": "day5_order1",
                "avatarName": "上班族",
                "customerName": "小陈",
                "showTime": [
                    8,
                    30
                ],
                "expireTime": [
                    9,
                    0
                ],
                "content": "多料鸡蛋冷面",
                "remark": "冷面皮一份刷油，两个鸡蛋，抹调味酱，加两片洋葱、三片生菜、一根火腿肠和一点辣白菜",
                "order": {
                    "冷面皮": {
                        "type": "撒料类",
                        "need": 1,
                        "count": 1
                    },
                    "鸡蛋": {
                        "type": "撒料类",
                        "need": 1,
                        "count": 2
                    },
                    "油": {
                        "type": "撒料类",
                        "need": 1,
                        "count": 1
                    },
                    "洋葱": {
                        "type": "撒料类",
                        "need": 1,
                        "count": 2
                    },
                    "调味酱": {
                        "type": "撒料类",
                        "need": 1,
                        "count": 1
                    },
                    "生菜": {
                        "type": "撒料类",
                        "need": 1,
                        "count": 3
                    },
                    "火腿肠": {
                        "type": "撒料类",
                        "need": 1,
                        "count": 1
                    },
                    "辣白菜": {
                        "type": "撒料类",
                        "need": 1,
                        "count": 1
                    }
                }
            },
            {
                "id": "day5_order2",
                "avatarName": "便衣",
                "customerName": "老李",
                "showTime": [
                    9,
                    15
                ],
                "expireTime": [
                    9,
                    45
                ],
                "content": "经典鸡蛋冷面",
                "remark": "冷面皮一份刷油，三个鸡蛋，抹浅色酱，加一片洋葱、两片生菜、一块猪排和一点芝麻",
                "order": {
                    "冷面皮": {
                        "type": "撒料类",
                        "need": 1,
                        "count": 1
                    },
                    "鸡蛋": {
                        "type": "撒料类",
                        "need": 1,
                        "count": 3
                    },
                    "油": {
                        "type": "撒料类",
                        "need": 1,
                        "count": 1
                    },
                    "洋葱": {
                        "type": "撒料类",
                        "need": 1,
                        "count": 1
                    },
                    "浅色酱": {
                        "type": "撒料类",
                        "need": 1,
                        "count": 1
                    },
                    "生菜": {
                        "type": "撒料类",
                        "need": 1,
                        "count": 2
                    },
                    "猪排": {
                        "type": "撒料类",
                        "need": 1,
                        "count": 1
                    },
                    "芝麻": {
                        "type": "撒料类",
                        "need": 1,
                        "count": 1
                    }
                }
            },
            {
                "id": "day5_order3",
                "avatarName": "学生",
                "customerName": "小林",
                "showTime": [
                    10,
                    0
                ],
                "expireTime": [
                    10,
                    30
                ],
                "content": "实惠鸡蛋冷面",
                "remark": "冷面皮一份刷油，一个鸡蛋，抹花生酱，加一片洋葱、一片生菜、一根鸡柳和一点辣条",
                "order": {
                    "冷面皮": {
                        "type": "撒料类",
                        "need": 1,
                        "count": 1
                    },
                    "鸡蛋": {
                        "type": "撒料类",
                        "need": 1,
                        "count": 1
                    },
                    "油": {
                        "type": "撒料类",
                        "need": 1,
                        "count": 1
                    },
                    "洋葱": {
                        "type": "撒料类",
                        "need": 1,
                        "count": 1
                    },
                    "花生酱": {
                        "type": "撒料类",
                        "need": 1,
                        "count": 1
                    },
                    "生菜": {
                        "type": "撒料类",
                        "need": 1,
                        "count": 1
                    },
                    "鸡柳": {
                        "type": "撒料类",
                        "need": 1,
                        "count": 1
                    },
                    "辣条": {
                        "type": "撒料类",
                        "need": 1,
                        "count": 1
                    }
                }
            },
            {
                "id": "day5_order4",
                "avatarName": "美女",
                "customerName": "小苏",
                "showTime": [
                    11,
                    0
                ],
                "expireTime": [
                    11,
                    30
                ],
                "content": "清爽鸡蛋冷面",
                "remark": "冷面皮一份刷油，两个鸡蛋，抹调味酱，加半片洋葱、三片生菜、一点鱼片和少许芝麻",
                "order": {
                    "冷面皮": {
                        "type": "撒料类",
                        "need": 1,
                        "count": 1
                    },
                    "鸡蛋": {
                        "type": "撒料类",
                        "need": 1,
                        "count": 2
                    },
                    "油": {
                        "type": "撒料类",
                        "need": 1,
                        "count": 1
                    },
                    "洋葱": {
                        "type": "撒料类",
                        "need": 1,
                        "count": 1
                    },
                    "调味酱": {
                        "type": "撒料类",
                        "need": 1,
                        "count": 1
                    },
                    "生菜": {
                        "type": "撒料类",
                        "need": 1,
                        "count": 3
                    },
                    "鱼片": {
                        "type": "撒料类",
                        "need": 1,
                        "count": 1
                    },
                    "芝麻": {
                        "type": "撒料类",
                        "need": 1,
                        "count": 1
                    }
                }
            },
            {
                "id": "day5_order5",
                "avatarName": "体育",
                "customerName": "小青",
                "showTime": [
                    12,
                    15
                ],
                "expireTime": [
                    12,
                    45
                ],
                "content": "能量鸡蛋冷面",
                "remark": "冷面皮一份刷油，四个鸡蛋，抹花生酱，加两片洋葱、四片生菜、两块鸡柳和一根火腿肠",
                "order": {
                    "冷面皮": {
                        "type": "撒料类",
                        "need": 1,
                        "count": 1
                    },
                    "鸡蛋": {
                        "type": "撒料类",
                        "need": 1,
                        "count": 4
                    },
                    "油": {
                        "type": "撒料类",
                        "need": 1,
                        "count": 1
                    },
                    "洋葱": {
                        "type": "撒料类",
                        "need": 1,
                        "count": 2
                    },
                    "花生酱": {
                        "type": "撒料类",
                        "need": 1,
                        "count": 1
                    },
                    "生菜": {
                        "type": "撒料类",
                        "need": 1,
                        "count": 4
                    },
                    "鸡柳": {
                        "type": "撒料类",
                        "need": 1,
                        "count": 2
                    },
                    "火腿肠": {
                        "type": "撒料类",
                        "need": 1,
                        "count": 1
                    }
                }
            },
            {
                "id": "day5_order6",
                "avatarName": "包租婆",
                "customerName": "小红",
                "showTime": [
                    14,
                    0
                ],
                "expireTime": [
                    14,
                    30
                ],
                "content": "丰富鸡蛋冷面",
                "remark": "冷面皮一份刷油，两个鸡蛋，抹浅色酱，加一片洋葱、两片生菜、一块猪排、一点辣白菜和少许芝麻",
                "order": {
                    "冷面皮": {
                        "type": "撒料类",
                        "need": 1,
                        "count": 1
                    },
                    "鸡蛋": {
                        "type": "撒料类",
                        "need": 1,
                        "count": 2
                    },
                    "油": {
                        "type": "撒料类",
                        "need": 1,
                        "count": 1
                    },
                    "洋葱": {
                        "type": "撒料类",
                        "need": 1,
                        "count": 1
                    },
                    "浅色酱": {
                        "type": "撒料类",
                        "need": 1,
                        "count": 1
                    },
                    "生菜": {
                        "type": "撒料类",
                        "need": 1,
                        "count": 2
                    },
                    "猪排": {
                        "type": "撒料类",
                        "need": 1,
                        "count": 1
                    },
                    "辣白菜": {
                        "type": "撒料类",
                        "need": 1,
                        "count": 1
                    },
                    "芝麻": {
                        "type": "撒料类",
                        "need": 1,
                        "count": 1
                    }
                }
            },
            {
                "id": "day5_order7",
                "avatarName": "非主流",
                "customerName": "小蓝",
                "showTime": [
                    16,
                    0
                ],
                "expireTime": [
                    16,
                    30
                ],
                "content": "个性鸡蛋冷面",
                "remark": "冷面皮一份刷油，三个鸡蛋，抹调味酱，加一片洋葱、一片生菜、一点辣条、一块芝士和少许鱼片",
                "order": {
                    "冷面皮": {
                        "type": "撒料类",
                        "need": 1,
                        "count": 1
                    },
                    "鸡蛋": {
                        "type": "撒料类",
                        "need": 1,
                        "count": 3
                    },
                    "油": {
                        "type": "撒料类",
                        "need": 1,
                        "count": 1
                    },
                    "洋葱": {
                        "type": "撒料类",
                        "need": 1,
                        "count": 1
                    },
                    "调味酱": {
                        "type": "撒料类",
                        "need": 1,
                        "count": 1
                    },
                    "生菜": {
                        "type": "撒料类",
                        "need": 1,
                        "count": 1
                    },
                    "辣条": {
                        "type": "撒料类",
                        "need": 1,
                        "count": 1
                    },
                    "芝士": {
                        "type": "撒料类",
                        "need": 1,
                        "count": 1
                    },
                    "鱼片": {
                        "type": "撒料类",
                        "need": 1,
                        "count": 1
                    }
                }
            }
        ]
    }
]